nester_laga.py
nester_laga-1.3.0.dist-info/METADATA
nester_laga-1.3.0.dist-info/WHEEL
nester_laga-1.3.0.dist-info/top_level.txt
nester_laga-1.3.0.dist-info/RECORD
