Metadata-Version: 2.1
Name: nester-laga
Version: 1.3.0
Summary: Um impressor simples de listas aninhadas.
Home-page: http://lagabreu.org
Author: lagabreu
Author-email: lagabreu@yahoo.com.br
